biobox_analytics/.DS_Store
biobox_analytics/__init__.py
biobox_analytics/_setup.py
biobox_analytics/assets/ENSEMBL_NCBI_MAPPING.csv
biobox_analytics/assets/hpoa_extras.json
biobox_analytics/core/__init__.py
biobox_analytics/core/_concept.py
biobox_analytics/core/_edge.py
biobox_analytics/core/_node.py
biobox_analytics/core/_relationship_group.py
biobox_analytics/core/.ipynb_checkpoints/__init__-checkpoint.py
biobox_analytics/data/.DS_Store
biobox_analytics/data/__init__.py
biobox_analytics/data/adapters/.DS_Store
biobox_analytics/data/adapters/__init__.py
biobox_analytics/data/adapters/_base.py
biobox_analytics/data/adapters/.ipynb_checkpoints/_base-checkpoint.py
biobox_analytics/data/adapters/alliance_genome/__init__.py
biobox_analytics/data/adapters/chipseq/__init__.py
biobox_analytics/data/adapters/chipseq/_structs.py
biobox_analytics/data/adapters/chipseq/.ipynb_checkpoints/__init__-checkpoint.py
biobox_analytics/data/adapters/chipseq/.ipynb_checkpoints/_structs-checkpoint.py
biobox_analytics/data/adapters/genome/.DS_Store
biobox_analytics/data/adapters/genome/__init__.py
biobox_analytics/data/adapters/genome/_structs.py
biobox_analytics/data/adapters/genome/.ipynb_checkpoints/DebuggingNotebook-checkpoint.ipynb
biobox_analytics/data/adapters/genome/.ipynb_checkpoints/__init__-checkpoint.py
biobox_analytics/data/adapters/genome/.ipynb_checkpoints/genome-pydantic-checkpoint.py
biobox_analytics/data/adapters/go/__init__.py
biobox_analytics/data/adapters/go/_structs.py
biobox_analytics/data/adapters/go/.ipynb_checkpoints/__init__-checkpoint.py
biobox_analytics/data/adapters/mgi/__init__.py
biobox_analytics/data/adapters/rna_diffexp/__init__.py
biobox_analytics/data/adapters/rna_diffexp/_structs.py
biobox_analytics/data/adapters/rnaseq/__init__.py
biobox_analytics/data/adapters/rnaseq/_structs.py
biobox_analytics/data/adapters/scatac/.DS_Store
biobox_analytics/data/adapters/scatac/__init__.py
biobox_analytics/data/adapters/scatac/_structs.py
biobox_analytics-0.1.12.dist-info/LICENSE
biobox_analytics-0.1.12.dist-info/WHEEL
biobox_analytics-0.1.12.dist-info/METADATA
biobox_analytics-0.1.12.dist-info/RECORD
