Metadata-Version: 2.1
Name: biobox-analytics
Version: 0.1.12
Summary: BioBox CLI for data manipulation in python
Author-email: Christopher Li <chris@biobox.io>, Hamza Farooq <hamza@biobox.io>, Julian Mazzitelli <julian@biobox.io>
Classifier: Programming Language :: Python :: 3.10
Classifier: Programming Language :: Python :: 3.11
Requires-Dist: scanpy
Requires-Dist: gtfparse
Project-URL: Home, https://biobox.io
